d8s_ip_addresses/__init__.py
d8s_ip_addresses/ip_addresses.py
d8s_ip_addresses/ip_addresses_temp_utils.py
tests/__init__.py
tests/test_ip_addresses.py
d8s_ip_addresses-0.6.0.dist-info/COPYING
d8s_ip_addresses-0.6.0.dist-info/COPYING.LESSER
d8s_ip_addresses-0.6.0.dist-info/METADATA
d8s_ip_addresses-0.6.0.dist-info/WHEEL
d8s_ip_addresses-0.6.0.dist-info/top_level.txt
d8s_ip_addresses-0.6.0.dist-info/zip-safe
d8s_ip_addresses-0.6.0.dist-info/RECORD
