Metadata-Version: 2.1
Name: d8s-ip-addresses
Version: 0.6.0
Summary: Democritus functions for working with IP addresses.
Home-page: https://github.com/democritus-project/d8s-ip-addresses
Author: Floyd Hightower
Author-email: floyd.hightower27@gmail.com
License: GNU Lesser General Public License v3
Keywords: democritus,utility,python,IP addresses,ip-addresses-utility,
Platform: UNKNOWN
Classifier: Development Status :: 2 - Pre-Alpha
Classifier: Intended Audience :: Developers
Classifier: License :: OSI Approved :: GNU Lesser General Public License v3 or later (LGPLv3+)
Classifier: Natural Language :: English
Classifier: Programming Language :: Python :: 3
Classifier: Programming Language :: Python :: 3.4
Classifier: Programming Language :: Python :: 3.5
Classifier: Programming Language :: Python :: 3.6
Classifier: Programming Language :: Python :: 3.7
Classifier: Programming Language :: Python :: 3.8
Classifier: Programming Language :: Python :: 3.9
Requires-Dist: d8s-csv (==0.*)
Requires-Dist: d8s-hypothesis (==0.*)
Requires-Dist: d8s-networking (==0.*)
Requires-Dist: hypothesis
Requires-Dist: ioc-finder
Requires-Dist: importlib-metadata ; python_version < "3.8"
